{"concept":[{"code":"AP","designation":[{"language":"de","use":{"code":"display","system":"http://terminology.hl7.org/CodeSystem/designation-usage"},"value":"externe Applikatione"},{"language":"nl","use":{"code":"display","system":"http://terminology.hl7.org/CodeSystem/designation-usage"},"value":"Uitwendig gebruiken"}],"display":"Apply externally","property":[{"code":"status","valueCode":"deprecated"},{"code":"deprecationDate","valueDateTime":"1990-01"}]},{"code":"CH","designation":[{"language":"de","use":{"code":"display","system":"http://terminology.hl7.org/CodeSystem/designation-usage"},"value":"Kautablette"},{"language":"nl","use":{"code":"display","system":"http://terminology.hl7.org/CodeSystem/designation-usage"},"value":"Kauwen"}],"display":"Chew","property":[{"code":"status","valueCode":"deprecated"},{"code":"deprecationDate","valueDateTime":"1990-01"}]},{"code":"DU","designation":[{"language":"de","use":{"code":"display","system":"http://terminology.hl7.org/CodeSystem/designation-usage"},"value":"Puder"},{"language":"nl","use":{"code":"display","system":"http://terminology.hl7.org/CodeSystem/designation-usage"},"value":"Stof"}],"display":"Dust","property":[{"code":"status","valueCode":"deprecated"},{"code":"deprecationDate","valueDateTime":"1990-01"}]},{"code":"EA","designation":[{"language":"de","use":{"code":"display","system":"http://terminology.hl7.org/CodeSystem/designation-usage"},"value":"Ohr"},{"language":"nl","use":{"code":"display","system":"http://terminology.hl7.org/CodeSystem/designation-usage"},"value":"Oor"}],"display":"Ear","property":[{"code":"status","valueCode":"deprecated"},{"code":"deprecationDate","valueDateTime":"1990-01"}]},{"code":"EY","designation":[{"language":"de","use":{"code":"display","system":"http://terminology.hl7.org/CodeSystem/designation-usage"},"value":"Auge"},{"language":"nl","use":{"code":"display","system":"http://terminology.hl7.org/CodeSystem/designation-usage"},"value":"Oog"}],"display":"Eye","property":[{"code":"status","valueCode":"deprecated"},{"code":"deprecationDate","valueDateTime":"1990-01"}]},{"code":"IA","designation":[{"language":"de","use":{"code":"display","system":"http://terminology.hl7.org/CodeSystem/designation-usage"},"value":"intraarteriell"},{"language":"nl","use":{"code":"display","system":"http://terminology.hl7.org/CodeSystem/designation-usage"},"value":"Intro-arteriaal"}],"display":"Intro-arterial","property":[{"code":"status","valueCode":"deprecated"},{"code":"deprecationDate","valueDateTime":"1990-01"}]},{"code":"ID","designation":[{"language":"de","use":{"code":"display","system":"http://terminology.hl7.org/CodeSystem/designation-usage"},"value":"intradermal"},{"language":"nl","use":{"code":"display","system":"http://terminology.hl7.org/CodeSystem/designation-usage"},"value":"Intra-dermaal"}],"display":"Intra-dermal","property":[{"code":"status","valueCode":"deprecated"},{"code":"deprecationDate","valueDateTime":"1990-01"}]},{"code":"IF","designation":[{"language":"de","use":{"code":"display","system":"http://terminology.hl7.org/CodeSystem/designation-usage"},"value":"infiltrieren"},{"language":"nl","use":{"code":"display","system":"http://terminology.hl7.org/CodeSystem/designation-usage"},"value":"Infiltratie"}],"display":"Infiltrate","property":[{"code":"status","valueCode":"deprecated"},{"code":"deprecationDate","valueDateTime":"1990-01"}]},{"code":"IH","designation":[{"language":"de","use":{"code":"display","system":"http://terminology.hl7.org/CodeSystem/designation-usage"},"value":"Inhalation"},{"language":"nl","use":{"code":"display","system":"http://terminology.hl7.org/CodeSystem/designation-usage"},"value":"Inhalatie"}],"display":"Inhalation","property":[{"code":"status","valueCode":"deprecated"},{"code":"deprecationDate","valueDateTime":"1990-01"}]},{"code":"IM","designation":[{"language":"de","use":{"code":"display","system":"http://terminology.hl7.org/CodeSystem/designation-usage"},"value":"intramuskulär"},{"language":"nl","use":{"code":"display","system":"http://terminology.hl7.org/CodeSystem/designation-usage"},"value":"Intra-musculair"}],"display":"Intra-muscular","property":[{"code":"status","valueCode":"deprecated"},{"code":"deprecationDate","valueDateTime":"1990-01"}]},{"code":"IN","designation":[{"language":"de","use":{"code":"display","system":"http://terminology.hl7.org/CodeSystem/designation-usage"},"value":"intranasal"},{"language":"nl","use":{"code":"display","system":"http://terminology.hl7.org/CodeSystem/designation-usage"},"value":"Intro-nasaal"}],"display":"Intra-nasal","property":[{"code":"status","valueCode":"deprecated"},{"code":"deprecationDate","valueDateTime":"1990-01"}]},{"code":"IR","designation":[{"language":"de","use":{"code":"display","system":"http://terminology.hl7.org/CodeSystem/designation-usage"},"value":"Einlauf"},{"language":"nl","use":{"code":"display","system":"http://terminology.hl7.org/CodeSystem/designation-usage"},"value":"Irrigatie"}],"display":"Irrigate","property":[{"code":"status","valueCode":"deprecated"},{"code":"deprecationDate","valueDateTime":"1990-01"}]},{"code":"IS","designation":[{"language":"de","use":{"code":"display","system":"http://terminology.hl7.org/CodeSystem/designation-usage"},"value":"Implantat"},{"language":"nl","use":{"code":"display","system":"http://terminology.hl7.org/CodeSystem/designation-usage"},"value":"Ingebracht"}],"display":"Inserted","property":[{"code":"status","valueCode":"deprecated"},{"code":"deprecationDate","valueDateTime":"1990-01"}]},{"code":"IT","designation":[{"language":"de","use":{"code":"display","system":"http://terminology.hl7.org/CodeSystem/designation-usage"},"value":"intrathekal"},{"language":"nl","use":{"code":"display","system":"http://terminology.hl7.org/CodeSystem/designation-usage"},"value":"Intrathecaal"}],"display":"Intrathecal","property":[{"code":"status","valueCode":"deprecated"},{"code":"deprecationDate","valueDateTime":"1990-01"}]},{"code":"IV","designation":[{"language":"de","use":{"code":"display","system":"http://terminology.hl7.org/CodeSystem/designation-usage"},"value":"intravenös"},{"language":"nl","use":{"code":"display","system":"http://terminology.hl7.org/CodeSystem/designation-usage"},"value":"Intraveneus"}],"display":"Intravenous","property":[{"code":"status","valueCode":"deprecated"},{"code":"deprecationDate","valueDateTime":"1990-01"}]},{"code":"NB","designation":[{"language":"de","use":{"code":"display","system":"http://terminology.hl7.org/CodeSystem/designation-usage"},"value":"vernebelt"},{"language":"nl","use":{"code":"display","system":"http://terminology.hl7.org/CodeSystem/designation-usage"},"value":"Verneveld"}],"display":"Nebulized","property":[{"code":"status","valueCode":"deprecated"},{"code":"deprecationDate","valueDateTime":"1990-01"}]},{"code":"NG","designation":[{"language":"de","use":{"code":"display","system":"http://terminology.hl7.org/CodeSystem/designation-usage"},"value":"nasogastral"}],"display":"Nathogasic","property":[{"code":"status","valueCode":"deprecated"},{"code":"deprecationDate","valueDateTime":"1990-01"}]},{"code":"PA","designation":[{"language":"de","use":{"code":"display","system":"http://terminology.hl7.org/CodeSystem/designation-usage"},"value":"peranal"},{"language":"nl","use":{"code":"display","system":"http://terminology.hl7.org/CodeSystem/designation-usage"},"value":"Peri-anaal"}],"display":"Peri-anally","property":[{"code":"status","valueCode":"deprecated"},{"code":"deprecationDate","valueDateTime":"1990-01"}]},{"code":"PT","designation":[{"language":"de","use":{"code":"display","system":"http://terminology.hl7.org/CodeSystem/designation-usage"},"value":"aufpinseln"},{"language":"nl","use":{"code":"display","system":"http://terminology.hl7.org/CodeSystem/designation-usage"},"value":"Verf"}],"display":"Paint","property":[{"code":"status","valueCode":"deprecated"},{"code":"deprecationDate","valueDateTime":"1990-01"}]},{"code":"PU","designation":[{"language":"de","use":{"code":"display","system":"http://terminology.hl7.org/CodeSystem/designation-usage"},"value":"intravenöser Bolus"},{"language":"nl","use":{"code":"display","system":"http://terminology.hl7.org/CodeSystem/designation-usage"},"value":"IV push"}],"display":"IV push","property":[{"code":"status","valueCode":"deprecated"},{"code":"deprecationDate","valueDateTime":"1990-01"}]},{"code":"RC","designation":[{"language":"de","use":{"code":"display","system":"http://terminology.hl7.org/CodeSystem/designation-usage"},"value":"rektal"},{"language":"nl","use":{"code":"display","system":"http://terminology.hl7.org/CodeSystem/designation-usage"},"value":"Rectaal"}],"display":"Rectally","property":[{"code":"status","valueCode":"deprecated"},{"code":"deprecationDate","valueDateTime":"1990-01"}]},{"code":"SH","designation":[{"language":"de","use":{"code":"display","system":"http://terminology.hl7.org/CodeSystem/designation-usage"},"value":"Shampoo"},{"language":"nl","use":{"code":"display","system":"http://terminology.hl7.org/CodeSystem/designation-usage"},"value":"Shampoo"}],"display":"Shampoo","property":[{"code":"status","valueCode":"deprecated"},{"code":"deprecationDate","valueDateTime":"1990-01"}]},{"code":"SL","designation":[{"language":"de","use":{"code":"display","system":"http://terminology.hl7.org/CodeSystem/designation-usage"},"value":"subligual"},{"language":"nl","use":{"code":"display","system":"http://terminology.hl7.org/CodeSystem/designation-usage"},"value":"Sublinguaal"}],"display":"Sublingual","property":[{"code":"status","valueCode":"deprecated"},{"code":"deprecationDate","valueDateTime":"1990-01"}]},{"code":"SO","designation":[{"language":"de","use":{"code":"display","system":"http://terminology.hl7.org/CodeSystem/designation-usage"},"value":"drchtränken"},{"language":"nl","use":{"code":"display","system":"http://terminology.hl7.org/CodeSystem/designation-usage"},"value":"Soppen"}],"display":"Soak","property":[{"code":"status","valueCode":"deprecated"},{"code":"deprecationDate","valueDateTime":"1990-01"}]},{"code":"SS","designation":[{"language":"de","use":{"code":"display","system":"http://terminology.hl7.org/CodeSystem/designation-usage"},"value":"Iv-Lösung"},{"language":"nl","use":{"code":"display","system":"http://terminology.hl7.org/CodeSystem/designation-usage"},"value":"IV soluset"}],"display":"IV soluset","property":[{"code":"status","valueCode":"deprecated"},{"code":"deprecationDate","valueDateTime":"1990-01"}]},{"code":"TP","designation":[{"language":"de","use":{"code":"display","system":"http://terminology.hl7.org/CodeSystem/designation-usage"},"value":"topisch"},{"language":"nl","use":{"code":"display","system":"http://terminology.hl7.org/CodeSystem/designation-usage"},"value":"Topicaal"}],"display":"Topically","property":[{"code":"status","valueCode":"deprecated"},{"code":"deprecationDate","valueDateTime":"1990-01"}]},{"code":"WA","designation":[{"language":"de","use":{"code":"display","system":"http://terminology.hl7.org/CodeSystem/designation-usage"},"value":"waschen"},{"language":"nl","use":{"code":"display","system":"http://terminology.hl7.org/CodeSystem/designation-usage"},"value":"Wassen"}],"display":"Wash","property":[{"code":"status","valueCode":"deprecated"},{"code":"deprecationDate","valueDateTime":"1990-01"}]},{"code":"WI","designation":[{"language":"de","use":{"code":"display","system":"http://terminology.hl7.org/CodeSystem/designation-usage"},"value":"wischen"},{"language":"nl","use":{"code":"display","system":"http://terminology.hl7.org/CodeSystem/designation-usage"},"value":"Vegen"}],"display":"Wipe","property":[{"code":"status","valueCode":"deprecated"},{"code":"deprecationDate","valueDateTime":"1990-01"}]}],"contact":[{"telecom":[{"system":"url","value":"http://hl7.org"}]}],"content":"complete","description":"FHIR Value set/code system definition for HL7 v2 table 0033 ( ROUTE)","experimental":false,"extension":[{"url":"http://hl7.org/fhir/StructureDefinition/structuredefinition-standards-status","valueCode":"external"},{"url":"http://hl7.org/fhir/StructureDefinition/structuredefinition-fmm","valueInteger":0}],"id":"v2-0033","identifier":[{"system":"urn:ietf:rfc:3986","value":"urn:oid:2.16.840.1.113883.18.16"}],"language":"en","meta":{"profile":["http://hl7.org/fhir/StructureDefinition/shareablecodesystem"]},"name":"v2.0033","property":[{"code":"status","description":"A property that indicates the status of the concept. One of active, experimental, deprecated, retired","type":"code","uri":"http://hl7.org/fhir/concept-properties#status"},{"code":"deprecationDate","description":"The date at which a concept was deprecated. Concepts that are deprecated but not inactive can still be used, but their use is discouraged","type":"dateTime","uri":"http://hl7.org/fhir/concept-properties#deprecationDate"}],"publisher":"HL7, Inc","resourceType":"CodeSystem","status":"active","text":{"div":"<div xmlns=\"http://www.w3.org/1999/xhtml\"><p>ROUTE</p>\r\n<table class=\"grid\"><tr><td><b>Code</b></td><td><b>Description</b></td><td><b>Comment</b></td><td><b>Version</b></td></tr><tr><td>AP<a name=\"AP\"> </a></td><td>Apply externally</td><td>deprecated</td><td>from v2.1, removed after v2.1</td></tr><tr><td>CH<a name=\"CH\"> </a></td><td>Chew</td><td>deprecated</td><td>from v2.1, removed after v2.1</td></tr><tr><td>DU<a name=\"DU\"> </a></td><td>Dust</td><td>deprecated</td><td>from v2.1, removed after v2.1</td></tr><tr><td>EA<a name=\"EA\"> </a></td><td>Ear</td><td>deprecated</td><td>from v2.1, removed after v2.1</td></tr><tr><td>EY<a name=\"EY\"> </a></td><td>Eye</td><td>deprecated</td><td>from v2.1, removed after v2.1</td></tr><tr><td>IA<a name=\"IA\"> </a></td><td>Intro-arterial</td><td>deprecated</td><td>from v2.1, removed after v2.1</td></tr><tr><td>ID<a name=\"ID\"> </a></td><td>Intra-dermal</td><td>deprecated</td><td>from v2.1, removed after v2.1</td></tr><tr><td>IF<a name=\"IF\"> </a></td><td>Infiltrate</td><td>deprecated</td><td>from v2.1, removed after v2.1</td></tr><tr><td>IH<a name=\"IH\"> </a></td><td>Inhalation</td><td>deprecated</td><td>from v2.1, removed after v2.1</td></tr><tr><td>IM<a name=\"IM\"> </a></td><td>Intra-muscular</td><td>deprecated</td><td>from v2.1, removed after v2.1</td></tr><tr><td>IN<a name=\"IN\"> </a></td><td>Intra-nasal</td><td>deprecated</td><td>from v2.1, removed after v2.1</td></tr><tr><td>IR<a name=\"IR\"> </a></td><td>Irrigate</td><td>deprecated</td><td>from v2.1, removed after v2.1</td></tr><tr><td>IS<a name=\"IS\"> </a></td><td>Inserted</td><td>deprecated</td><td>from v2.1, removed after v2.1</td></tr><tr><td>IT<a name=\"IT\"> </a></td><td>Intrathecal</td><td>deprecated</td><td>from v2.1, removed after v2.1</td></tr><tr><td>IV<a name=\"IV\"> </a></td><td>Intravenous</td><td>deprecated</td><td>from v2.1, removed after v2.1</td></tr><tr><td>NB<a name=\"NB\"> </a></td><td>Nebulized</td><td>deprecated</td><td>from v2.1, removed after v2.1</td></tr><tr><td>NG<a name=\"NG\"> </a></td><td>Nathogasic</td><td>deprecated</td><td>from v2.1, removed after v2.1</td></tr><tr><td>PA<a name=\"PA\"> </a></td><td>Peri-anally</td><td>deprecated</td><td>from v2.1, removed after v2.1</td></tr><tr><td>PT<a name=\"PT\"> </a></td><td>Paint</td><td>deprecated</td><td>from v2.1, removed after v2.1</td></tr><tr><td>PU<a name=\"PU\"> </a></td><td>IV push</td><td>deprecated</td><td>from v2.1, removed after v2.1</td></tr><tr><td>RC<a name=\"RC\"> </a></td><td>Rectally</td><td>deprecated</td><td>from v2.1, removed after v2.1</td></tr><tr><td>SH<a name=\"SH\"> </a></td><td>Shampoo</td><td>deprecated</td><td>from v2.1, removed after v2.1</td></tr><tr><td>SL<a name=\"SL\"> </a></td><td>Sublingual</td><td>deprecated</td><td>from v2.1, removed after v2.1</td></tr><tr><td>SO<a name=\"SO\"> </a></td><td>Soak</td><td>deprecated</td><td>from v2.1, removed after v2.1</td></tr><tr><td>SS<a name=\"SS\"> </a></td><td>IV soluset</td><td>deprecated</td><td>from v2.1, removed after v2.1</td></tr><tr><td>TP<a name=\"TP\"> </a></td><td>Topically</td><td>deprecated</td><td>from v2.1, removed after v2.1</td></tr><tr><td>WA<a name=\"WA\"> </a></td><td>Wash</td><td>deprecated</td><td>from v2.1, removed after v2.1</td></tr><tr><td>WI<a name=\"WI\"> </a></td><td>Wipe</td><td>deprecated</td><td>from v2.1, removed after v2.1</td></tr></table>\r\n</div>","status":"additional"},"title":"v2 ROUTE","url":"http://terminology.hl7.org/CodeSystem/v2-0033","version":"2.9"}