{"concept":[{"code":"BP","designation":[{"language":"de","use":{"code":"display","system":"http://terminology.hl7.org/CodeSystem/designation-usage"},"value":"Kontaktperson für Abrechnung"},{"language":"nl","use":{"code":"display","system":"http://terminology.hl7.org/CodeSystem/designation-usage"},"value":"Facturatie contactpersoon"}],"display":"Billing contact person","property":[{"code":"status","valueCode":"deprecated"},{"code":"deprecationDate","valueDateTime":"1997-03"}]},{"code":"C","designation":[{"language":"de","use":{"code":"display","system":"http://terminology.hl7.org/CodeSystem/designation-usage"},"value":"Ansprechpartner in Notfällen"},{"language":"nl","use":{"code":"display","system":"http://terminology.hl7.org/CodeSystem/designation-usage"},"value":"Contact bij nood"}],"display":"Emergency Contact"},{"code":"CP","designation":[{"language":"de","use":{"code":"display","system":"http://terminology.hl7.org/CodeSystem/designation-usage"},"value":"Kontaktperson"},{"language":"nl","use":{"code":"display","system":"http://terminology.hl7.org/CodeSystem/designation-usage"},"value":"Contactpersoon"}],"display":"Contact person","property":[{"code":"status","valueCode":"deprecated"},{"code":"deprecationDate","valueDateTime":"1997-03"}]},{"code":"E","designation":[{"language":"de","use":{"code":"display","system":"http://terminology.hl7.org/CodeSystem/designation-usage"},"value":"Arbeitgeber"},{"language":"nl","use":{"code":"display","system":"http://terminology.hl7.org/CodeSystem/designation-usage"},"value":"Werkgever"}],"display":"Employer"},{"code":"EP","designation":[{"language":"de","use":{"code":"display","system":"http://terminology.hl7.org/CodeSystem/designation-usage"},"value":"Kontaktperson für Notfälle"},{"language":"nl","use":{"code":"display","system":"http://terminology.hl7.org/CodeSystem/designation-usage"},"value":"Contactpersoon bij nood"}],"display":"Emergency contact person","property":[{"code":"status","valueCode":"deprecated"},{"code":"deprecationDate","valueDateTime":"1997-03"}]},{"code":"F","designation":[{"language":"de","use":{"code":"display","system":"http://terminology.hl7.org/CodeSystem/designation-usage"},"value":"Bundesbehörde"},{"language":"nl","use":{"code":"display","system":"http://terminology.hl7.org/CodeSystem/designation-usage"},"value":"Federale overheidsinstelling"}],"display":"Federal Agency"},{"code":"I","designation":[{"language":"de","use":{"code":"display","system":"http://terminology.hl7.org/CodeSystem/designation-usage"},"value":"Versicherung"},{"language":"nl","use":{"code":"display","system":"http://terminology.hl7.org/CodeSystem/designation-usage"},"value":"Verzekeraar"}],"display":"Insurance Company"},{"code":"N","designation":[{"language":"de","use":{"code":"display","system":"http://terminology.hl7.org/CodeSystem/designation-usage"},"value":"Kontaktperson"},{"language":"nl","use":{"code":"display","system":"http://terminology.hl7.org/CodeSystem/designation-usage"},"value":"Familielid"}],"display":"Next-of-Kin"},{"code":"O","designation":[{"language":"de","use":{"code":"display","system":"http://terminology.hl7.org/CodeSystem/designation-usage"},"value":"andere"},{"language":"nl","use":{"code":"display","system":"http://terminology.hl7.org/CodeSystem/designation-usage"},"value":"Anders"}],"display":"Other"},{"code":"PR","designation":[{"language":"de","use":{"code":"display","system":"http://terminology.hl7.org/CodeSystem/designation-usage"},"value":"Person, die die Überweisung vorbereitet"},{"language":"nl","use":{"code":"display","system":"http://terminology.hl7.org/CodeSystem/designation-usage"},"value":"Persoon die verwijzing voorbereidt"}],"display":"Person preparing referral","property":[{"code":"status","valueCode":"deprecated"},{"code":"deprecationDate","valueDateTime":"1997-03"}]},{"code":"S","designation":[{"language":"de","use":{"code":"display","system":"http://terminology.hl7.org/CodeSystem/designation-usage"},"value":"Landesbehörde"},{"language":"nl","use":{"code":"display","system":"http://terminology.hl7.org/CodeSystem/designation-usage"},"value":"Staat overheidsinstelling"}],"display":"State Agency"},{"code":"U","designation":[{"language":"de","use":{"code":"display","system":"http://terminology.hl7.org/CodeSystem/designation-usage"},"value":"unbekannt"},{"language":"nl","use":{"code":"display","system":"http://terminology.hl7.org/CodeSystem/designation-usage"},"value":"Onbekend"}],"display":"Unknown"}],"contact":[{"telecom":[{"system":"url","value":"http://hl7.org"}]}],"content":"complete","description":"FHIR Value set/code system definition for HL7 v2 table 0131 ( Contact Role)","experimental":false,"extension":[{"url":"http://hl7.org/fhir/StructureDefinition/structuredefinition-standards-status","valueCode":"normative"},{"url":"http://hl7.org/fhir/StructureDefinition/structuredefinition-fmm","valueInteger":5},{"url":"http://hl7.org/fhir/StructureDefinition/structuredefinition-wg","valueCode":"pa"},{"url":"http://hl7.org/fhir/StructureDefinition/structuredefinition-normative-version","valueCode":"4.0.0"}],"id":"v2-0131","identifier":[{"system":"urn:ietf:rfc:3986","value":"urn:oid:2.16.840.1.113883.18.58"}],"language":"en","meta":{"profile":["http://hl7.org/fhir/StructureDefinition/shareablecodesystem"]},"name":"v2.0131","property":[{"code":"status","description":"A property that indicates the status of the concept. One of active, experimental, deprecated, retired","type":"code","uri":"http://hl7.org/fhir/concept-properties#status"},{"code":"deprecationDate","description":"The date at which a concept was deprecated. Concepts that are deprecated but not inactive can still be used, but their use is discouraged","type":"dateTime","uri":"http://hl7.org/fhir/concept-properties#deprecationDate"}],"publisher":"HL7, Inc","resourceType":"CodeSystem","status":"active","text":{"div":"<div xmlns=\"http://www.w3.org/1999/xhtml\"><p>Contact Role</p>\r\n<table class=\"grid\"><tr><td><b>Code</b></td><td><b>Description</b></td><td><b>Comment</b></td><td><b>Version</b></td></tr><tr><td>BP<a name=\"BP\"> </a></td><td>Billing contact person</td><td>deprecated</td><td>added v2.3, removed after v2.3</td></tr><tr><td>C<a name=\"C\"> </a></td><td>Emergency Contact</td><td/><td>added v2.5</td></tr><tr><td>CP<a name=\"CP\"> </a></td><td>Contact person</td><td>deprecated</td><td>added v2.3, removed after v2.3</td></tr><tr><td>E<a name=\"E\"> </a></td><td>Employer</td><td/><td>added v2.5</td></tr><tr><td>EP<a name=\"EP\"> </a></td><td>Emergency contact person</td><td>deprecated</td><td>added v2.3, removed after v2.3</td></tr><tr><td>F<a name=\"F\"> </a></td><td>Federal Agency</td><td/><td>added v2.5</td></tr><tr><td>I<a name=\"I\"> </a></td><td>Insurance Company</td><td/><td>added v2.5</td></tr><tr><td>N<a name=\"N\"> </a></td><td>Next-of-Kin</td><td/><td>added v2.5</td></tr><tr><td>O<a name=\"O\"> </a></td><td>Other</td><td/><td>added v2.5</td></tr><tr><td>PR<a name=\"PR\"> </a></td><td>Person preparing referral</td><td>deprecated</td><td>added v2.3, removed after v2.3</td></tr><tr><td>S<a name=\"S\"> </a></td><td>State Agency</td><td/><td>added v2.5</td></tr><tr><td>U<a name=\"U\"> </a></td><td>Unknown</td><td/><td>added v2.5</td></tr></table>\r\n</div>","status":"additional"},"title":"v2 Contact Role","url":"http://terminology.hl7.org/CodeSystem/v2-0131","version":"2.9"}